zh_langchain/__init__.py
zh_langchain/api.py
zh_langchain/cli.py
zh_langchain/cli_demo.py
zh_langchain/cradle.py
zh_langchain/release.py
zh_langchain/webui.py
zh_langchain/zh_langchain.py
zh_langchain/agent/__init__.py
zh_langchain/chains/__init__.py
zh_langchain/chains/local_doc_qa.py
zh_langchain/chains/text_load.py
zh_langchain/configs/__init__.py
zh_langchain/configs/model_config.py
zh_langchain/loader/__init__.py
zh_langchain/loader/image_loader.py
zh_langchain/loader/pdf_loader.py
zh_langchain/models/__init__.py
zh_langchain/nltk_data/corpora/cmudict/README
zh_langchain/nltk_data/corpora/cmudict/cmudict
zh_langchain/nltk_data/taggers/averaged_perceptron_tagger/averaged_perceptron_tagger.pickle
zh_langchain/nltk_data/tokenizers/punkt/README
zh_langchain/nltk_data/tokenizers/punkt/czech.pickle
zh_langchain/nltk_data/tokenizers/punkt/danish.pickle
zh_langchain/nltk_data/tokenizers/punkt/dutch.pickle
zh_langchain/nltk_data/tokenizers/punkt/english.pickle
zh_langchain/nltk_data/tokenizers/punkt/estonian.pickle
zh_langchain/nltk_data/tokenizers/punkt/finnish.pickle
zh_langchain/nltk_data/tokenizers/punkt/french.pickle
zh_langchain/nltk_data/tokenizers/punkt/german.pickle
zh_langchain/nltk_data/tokenizers/punkt/greek.pickle
zh_langchain/nltk_data/tokenizers/punkt/italian.pickle
zh_langchain/nltk_data/tokenizers/punkt/malayalam.pickle
zh_langchain/nltk_data/tokenizers/punkt/norwegian.pickle
zh_langchain/nltk_data/tokenizers/punkt/polish.pickle
zh_langchain/nltk_data/tokenizers/punkt/portuguese.pickle
zh_langchain/nltk_data/tokenizers/punkt/russian.pickle
zh_langchain/nltk_data/tokenizers/punkt/slovene.pickle
zh_langchain/nltk_data/tokenizers/punkt/spanish.pickle
zh_langchain/nltk_data/tokenizers/punkt/swedish.pickle
zh_langchain/nltk_data/tokenizers/punkt/turkish.pickle
zh_langchain/nltk_data/tokenizers/punkt/PY3/README
zh_langchain/nltk_data/tokenizers/punkt/PY3/czech.pickle
zh_langchain/nltk_data/tokenizers/punkt/PY3/danish.pickle
zh_langchain-0.2.1.dist-info/METADATA
zh_langchain-0.2.1.dist-info/WHEEL
zh_langchain-0.2.1.dist-info/top_level.txt
zh_langchain-0.2.1.dist-info/RECORD
