Metadata-Version: 2.1
Name: zh-langchain
Version: 0.2.1
Summary: Chinese language processing library
Home-page: https://github.com/imClumsyPanda/langchain-ChatGLM.git
Author: chatglm-langchain
Author-email: your.email@github.com
Classifier: Development Status :: 3 - Alpha
Classifier: Intended Audience :: Developers
Classifier: License :: OSI Approved :: MIT License
Classifier: Programming Language :: Python :: 3
Requires-Dist: torch
Requires-Dist: langchain
Requires-Dist: unstructured[local-inference]
Requires-Dist: nltk
Requires-Dist: sentence-transformers
Requires-Dist: beautifulsoup4
Requires-Dist: icetk
Requires-Dist: cpm-kernels
Requires-Dist: faiss-cpu
Requires-Dist: bitsandbytes
Requires-Dist: tabulate
